{
  "possibilities": {
    "chatWorker": {
      "outcomes": {
        "0": {
          "effect": "occupied",
          "lostTime": 60,
          "randomItem": {}
        },
        "1": {
          "effect": "occupied",
          "lostTime": 10
        },
        "2": {
          "effect": "injured",
          "health": -70
        }
      }
    },
    "end": {
      "outcomes": {
        "0": {
          "effect": "occupied",
          "lostTime": 30
        }
      }
    },
    "goAway": {
      "outcomes": {
        "0": {},
        "1": {
          "effect": "occupied",
          "lostTime": 20
        },
        "2": {
          "effect": "sleeping",
          "health": -20
        }
      }
    },
    "stayNight": {
      "outcomes": {
        "0": {
          "effect": "sleeping",
          "health": 10
        },
        "1": {
          "effect": "occupied",
          "lostTime": 5
        },
        "2": {},
        "3": {
          "effect": "occupied",
          "health": 5,
          "lostTime": 100
        }
      }
    }
  },
  "triggers": [
    {
      "mapId": 12
    }
  ]
}